{
  "annotations": { "list": [] },
  "editable": true,
  "fiscalYearStartMonth": 0,
  "graphTooltip": 1,
  "id": null,
  "links": [],
  "panels": [
    {
      "datasource": "Prometheus",
      "fieldConfig": {
        "defaults": {
          "color": { "mode": "thresholds" },
          "mappings": [],
          "thresholds": {
            "mode": "absolute",
            "steps": [
              { "color": "green", "value": null },
              { "color": "yellow", "value": 70 },
              { "color": "red", "value": 90 }
            ]
          },
          "unit": "percent",
          "min": 0,
          "max": 100
        },
        "overrides": []
      },
      "gridPos": { "h": 8, "w": 24, "x": 0, "y": 0 },
      "id": 1,
      "options": {
        "displayMode": "gradient",
        "minVizHeight": 10,
        "minVizWidth": 0,
        "orientation": "horizontal",
        "reduceOptions": { "calcs": ["lastNotNull"], "fields": "", "values": false },
        "showUnfilled": true,
        "text": {}
      },
      "pluginVersion": "9.0.0",
      "title": "GPU Utilization per Node",
      "type": "bargauge",
      "targets": [
        {
          "datasource": "Prometheus",
          "expr": "DCGM_FI_DEV_GPU_UTIL{job=\"gpu_metrics\"}",
          "legendFormat": "{{instance}}",
          "refId": "A"
        },
        {
          "datasource": "Prometheus",
          "expr": "nvidia_smi_utilization_gpu_ratio{job=\"gpu_metrics\"} * 100",
          "legendFormat": "{{instance}}",
          "refId": "B"
        }
      ]
    },
    {
      "datasource": "Prometheus",
      "fieldConfig": {
        "defaults": {
          "color": { "mode": "thresholds" },
          "thresholds": {
            "mode": "absolute",
            "steps": [
              { "color": "green", "value": null },
              { "color": "yellow", "value": 70 },
              { "color": "red", "value": 85 }
            ]
          },
          "unit": "celsius",
          "min": 0,
          "max": 100
        },
        "overrides": []
      },
      "gridPos": { "h": 8, "w": 24, "x": 0, "y": 8 },
      "id": 2,
      "options": {
        "displayMode": "gradient",
        "orientation": "horizontal",
        "reduceOptions": { "calcs": ["lastNotNull"], "fields": "", "values": false },
        "showUnfilled": true
      },
      "title": "GPU Temperature per Node",
      "type": "bargauge",
      "targets": [
        {
          "datasource": "Prometheus",
          "expr": "DCGM_FI_DEV_GPU_TEMP{job=\"gpu_metrics\"}",
          "legendFormat": "{{instance}}",
          "refId": "A"
        },
        {
          "datasource": "Prometheus",
          "expr": "nvidia_smi_temperature_gpu{job=\"gpu_metrics\"}",
          "legendFormat": "{{instance}}",
          "refId": "B"
        }
      ]
    },
    {
      "datasource": "Prometheus",
      "fieldConfig": {
        "defaults": {
          "color": { "mode": "thresholds" },
          "thresholds": {
            "mode": "absolute",
            "steps": [
              { "color": "green", "value": null },
              { "color": "yellow", "value": 70 },
              { "color": "red", "value": 90 }
            ]
          },
          "unit": "percent",
          "min": 0,
          "max": 100
        },
        "overrides": []
      },
      "gridPos": { "h": 8, "w": 24, "x": 0, "y": 16 },
      "id": 3,
      "options": {
        "displayMode": "gradient",
        "orientation": "horizontal",
        "reduceOptions": { "calcs": ["lastNotNull"], "fields": "", "values": false },
        "showUnfilled": true
      },
      "title": "GPU Memory Used % per Node",
      "type": "bargauge",
      "targets": [
        {
          "datasource": "Prometheus",
          "expr": "DCGM_FI_DEV_FB_USED{job=\"gpu_metrics\"} / (DCGM_FI_DEV_FB_USED{job=\"gpu_metrics\"} + DCGM_FI_DEV_FB_FREE{job=\"gpu_metrics\"}) * 100",
          "legendFormat": "{{instance}}",
          "refId": "A"
        },
        {
          "datasource": "Prometheus",
          "expr": "nvidia_smi_memory_used_bytes{job=\"gpu_metrics\"} / nvidia_smi_memory_total_bytes{job=\"gpu_metrics\"} * 100",
          "legendFormat": "{{instance}}",
          "refId": "B"
        }
      ]
    },
    {
      "datasource": "Prometheus",
      "fieldConfig": {
        "defaults": {
          "color": { "mode": "palette-classic" },
          "custom": {
            "axisCenteredZero": false,
            "axisColorMode": "text",
            "axisLabel": "",
            "axisPlacement": "auto",
            "barAlignment": 0,
            "drawStyle": "line",
            "fillOpacity": 10,
            "gradientMode": "none",
            "hideFrom": { "legend": false, "tooltip": false, "viz": false },
            "lineInterpolation": "linear",
            "lineWidth": 1,
            "pointSize": 5,
            "scaleDistribution": { "type": "linear" },
            "showPoints": "never",
            "spanNulls": false,
            "stacking": { "group": "A", "mode": "none" },
            "thresholdsStyle": { "mode": "off" }
          },
          "unit": "percent",
          "min": 0,
          "max": 100
        },
        "overrides": []
      },
      "gridPos": { "h": 10, "w": 12, "x": 0, "y": 24 },
      "id": 4,
      "options": {
        "legend": { "calcs": ["mean", "max"], "displayMode": "table", "placement": "bottom" },
        "tooltip": { "mode": "multi", "sort": "desc" }
      },
      "title": "GPU Utilization Over Time",
      "type": "timeseries",
      "targets": [
        {
          "datasource": "Prometheus",
          "expr": "DCGM_FI_DEV_GPU_UTIL{job=\"gpu_metrics\"}",
          "legendFormat": "{{instance}}",
          "refId": "A"
        },
        {
          "datasource": "Prometheus",
          "expr": "nvidia_smi_utilization_gpu_ratio{job=\"gpu_metrics\"} * 100",
          "legendFormat": "{{instance}}",
          "refId": "B"
        }
      ]
    },
    {
      "datasource": "Prometheus",
      "fieldConfig": {
        "defaults": {
          "color": { "mode": "palette-classic" },
          "custom": {
            "drawStyle": "line",
            "fillOpacity": 10,
            "lineWidth": 1,
            "showPoints": "never",
            "spanNulls": false
          },
          "unit": "celsius"
        },
        "overrides": []
      },
      "gridPos": { "h": 10, "w": 12, "x": 12, "y": 24 },
      "id": 5,
      "options": {
        "legend": { "calcs": ["mean", "max"], "displayMode": "table", "placement": "bottom" },
        "tooltip": { "mode": "multi", "sort": "desc" }
      },
      "title": "GPU Temperature Over Time",
      "type": "timeseries",
      "targets": [
        {
          "datasource": "Prometheus",
          "expr": "DCGM_FI_DEV_GPU_TEMP{job=\"gpu_metrics\"}",
          "legendFormat": "{{instance}}",
          "refId": "A"
        },
        {
          "datasource": "Prometheus",
          "expr": "nvidia_smi_temperature_gpu{job=\"gpu_metrics\"}",
          "legendFormat": "{{instance}}",
          "refId": "B"
        }
      ]
    },
    {
      "datasource": "Prometheus",
      "fieldConfig": {
        "defaults": {
          "color": { "mode": "palette-classic" },
          "custom": {
            "drawStyle": "line",
            "fillOpacity": 10,
            "lineWidth": 1,
            "showPoints": "never"
          },
          "unit": "watt"
        },
        "overrides": []
      },
      "gridPos": { "h": 10, "w": 12, "x": 0, "y": 34 },
      "id": 6,
      "options": {
        "legend": { "calcs": ["mean", "max"], "displayMode": "table", "placement": "bottom" },
        "tooltip": { "mode": "multi", "sort": "desc" }
      },
      "title": "GPU Power Usage Over Time",
      "type": "timeseries",
      "targets": [
        {
          "datasource": "Prometheus",
          "expr": "DCGM_FI_DEV_POWER_USAGE{job=\"gpu_metrics\"}",
          "legendFormat": "{{instance}}",
          "refId": "A"
        },
        {
          "datasource": "Prometheus",
          "expr": "nvidia_smi_power_draw_watts{job=\"gpu_metrics\"}",
          "legendFormat": "{{instance}}",
          "refId": "B"
        }
      ]
    },
    {
      "datasource": "Prometheus",
      "fieldConfig": {
        "defaults": {
          "color": { "mode": "palette-classic" },
          "custom": {
            "drawStyle": "line",
            "fillOpacity": 10,
            "lineWidth": 1,
            "showPoints": "never"
          },
          "unit": "bytes"
        },
        "overrides": []
      },
      "gridPos": { "h": 10, "w": 12, "x": 12, "y": 34 },
      "id": 7,
      "options": {
        "legend": { "calcs": ["mean", "max"], "displayMode": "table", "placement": "bottom" },
        "tooltip": { "mode": "multi", "sort": "desc" }
      },
      "title": "GPU Memory Used Over Time",
      "type": "timeseries",
      "targets": [
        {
          "datasource": "Prometheus",
          "expr": "DCGM_FI_DEV_FB_USED{job=\"gpu_metrics\"} * 1024 * 1024",
          "legendFormat": "{{instance}}",
          "refId": "A"
        },
        {
          "datasource": "Prometheus",
          "expr": "nvidia_smi_memory_used_bytes{job=\"gpu_metrics\"}",
          "legendFormat": "{{instance}}",
          "refId": "B"
        }
      ]
    },
    {
      "datasource": "Prometheus",
      "fieldConfig": {
        "defaults": {
          "color": { "mode": "thresholds" },
          "thresholds": {
            "mode": "absolute",
            "steps": [
              { "color": "red", "value": null },
              { "color": "green", "value": 1 }
            ]
          },
          "mappings": [
            { "options": { "0": { "text": "DOWN" }, "1": { "text": "UP" } }, "type": "value" }
          ]
        },
        "overrides": []
      },
      "gridPos": { "h": 8, "w": 24, "x": 0, "y": 44 },
      "id": 8,
      "options": {
        "colorMode": "background",
        "graphMode": "none",
        "justifyMode": "auto",
        "orientation": "horizontal",
        "reduceOptions": { "calcs": ["lastNotNull"], "fields": "", "values": false },
        "textMode": "auto"
      },
      "title": "Node Status (UP / DOWN)",
      "type": "stat",
      "targets": [
        {
          "datasource": "Prometheus",
          "expr": "up{job=\"gpu_metrics\"}",
          "legendFormat": "{{instance}}",
          "refId": "A"
        }
      ]
    },
    {
      "datasource": "Prometheus",
      "description": "Explore all raw metrics from the GPU nodes — useful when metric names are unknown",
      "fieldConfig": {
        "defaults": { "color": { "mode": "palette-classic" } },
        "overrides": []
      },
      "gridPos": { "h": 10, "w": 24, "x": 0, "y": 52 },
      "id": 9,
      "options": {
        "legend": { "displayMode": "list", "placement": "bottom" },
        "tooltip": { "mode": "single", "sort": "none" }
      },
      "title": "All Metrics Explorer (edit query to explore)",
      "type": "timeseries",
      "targets": [
        {
          "datasource": "Prometheus",
          "expr": "{job=\"gpu_metrics\", instance=\"34.126.91.108:8764\"}",
          "legendFormat": "{{__name__}} | {{instance}}",
          "refId": "A"
        }
      ]
    }
  ],
  "refresh": "15s",
  "schemaVersion": 37,
  "style": "dark",
  "tags": ["gpu", "cluster"],
  "templating": {
    "list": [
      {
        "current": {},
        "datasource": "Prometheus",
        "definition": "label_values(up{job=\"gpu_metrics\"}, instance)",
        "hide": 0,
        "includeAll": true,
        "multi": true,
        "name": "instance",
        "options": [],
        "query": {
          "query": "label_values(up{job=\"gpu_metrics\"}, instance)",
          "refId": "StandardVariableQuery"
        },
        "refresh": 2,
        "regex": "",
        "sort": 1,
        "type": "query",
        "label": "GPU Node"
      }
    ]
  },
  "time": { "from": "now-1h", "to": "now" },
  "timepicker": {},
  "timezone": "browser",
  "title": "GPU Cluster Monitor",
  "uid": "gpu-cluster-monitor",
  "version": 1
}
